aiozaneapi/__init__.py
aiozaneapi-1.6.dist-info/LICENSE
aiozaneapi-1.6.dist-info/METADATA
aiozaneapi-1.6.dist-info/WHEEL
aiozaneapi-1.6.dist-info/top_level.txt
aiozaneapi-1.6.dist-info/RECORD
