Metadata-Version: 2.1
Name: aiozaneapi
Version: 1.6
Summary: An async wrapper made in Python for Zane API.
Home-page: http://github.com/kal-byte/aiozaneapi
Author: kal-byte
Author-email: UNKNOWN
License: MIT
Platform: UNKNOWN
